pan_genomics_download/__init__.py
pan_genomics_download/pan_genomics_download.py
pan_genomics_download-0.0.2.dist-info/LICENSE
pan_genomics_download-0.0.2.dist-info/METADATA
pan_genomics_download-0.0.2.dist-info/WHEEL
pan_genomics_download-0.0.2.dist-info/entry_points.txt
pan_genomics_download-0.0.2.dist-info/top_level.txt
pan_genomics_download-0.0.2.dist-info/RECORD
