Metadata-Version: 2.1
Name: pan-genomics-download
Version: 0.0.2
Summary: Download all files from pan.genomics.cn using a shared url.
Home-page: https://github.com/JaylanLiu/pan-genomics-download
Author: JaylanLiu
Author-email: liujilong@outlook.com
License: UNKNOWN
Platform: UNKNOWN
Classifier: Development Status :: 3 - Alpha
Classifier: Intended Audience :: Developers
Classifier: Topic :: Scientific/Engineering :: Bio-Informatics
Classifier: License :: OSI Approved :: MIT License
Classifier: Programming Language :: Python :: 3.5
Classifier: Programming Language :: Python :: 3.6
Classifier: Programming Language :: Python :: 3.7
Requires-Python: >=3.6
License-File: LICENSE
Requires-Dist: requests
